setup.cfg
setup.py
markdown2social/__init__.py
markdown2social/__main__.py
markdown2social/converter.py
markdown2social/converter_test.py
markdown2social/integration_test.py
markdown2social/metadata.py
markdown2social.egg-info/PKG-INFO
markdown2social.egg-info/SOURCES.txt
markdown2social.egg-info/dependency_links.txt
markdown2social.egg-info/entry_points.txt
markdown2social.egg-info/requires.txt
markdown2social.egg-info/top_level.txt