Metadata-Version: 1.1
Name: markdown2social
Version: 0.1
Summary: Converts Markdown documents to Google+ posts
Home-page: https://github.com/jmmv/markdown2social
Author: Julio Merino
Author-email: jmmv@google.com
License: Apache
Keywords: markdown converter googleplus social
Platform: UNKNOWN
Classifier: Development Status :: 4 - Beta
Classifier: Environment :: Console
Classifier: License :: OSI Approved :: Apache Software License
Classifier: Programming Language :: Python :: 2.7
Classifier: Topic :: Text Processing :: Markup
